riverit_rpa_mailer/__init__.py
riverit_rpa_mailer/riverit_rpa_mailer.py
riverit_rpa_mailer/resources/__init__.py
riverit_rpa_mailer/resources/email_template.html
riverit_rpa_mailer-1.1.1.dist-info/METADATA
riverit_rpa_mailer-1.1.1.dist-info/WHEEL
riverit_rpa_mailer-1.1.1.dist-info/licenses/LICENSE
riverit_rpa_mailer-1.1.1.dist-info/RECORD
