Metadata-Version: 2.3
Name: riverit-rpa-mailer
Version: 1.1.1
Summary: A mailer designed to be used by robots to send process reports
Author-email: Saku Ylimäki <saku.ylimaki@riverit.fi>
License:                                  Apache License
License-File: LICENSE
Classifier: Operating System :: OS Independent
Classifier: Programming Language :: Python :: 3
Requires-Python: >=3.10
Requires-Dist: msal>=1.31.0
